README.md
setup.cfg
setup.py
NASA/__init__.py
NASA/APOD/__init__.py
NASA/APOD/apod.py
NASA/DONKI/__init__.py
NASA/DONKI/donki.py
NASA/EONET/__init__.py
NASA/EONET/eonet.py
NASA/EPIC/__init__.py
NASA/EPIC/epic.py
NASA/Earth/__init__.py
NASA/Earth/earth.py
NASA/Exoplanet/__init__.py
NASA/Exoplanet/exoplanet.py
NASA/GeneLab/__init__.py
NASA/GeneLab/genelab.py
NASA/Images/__init__.py
NASA/Images/images.py
NASA/Insight/__init__.py
NASA/Insight/insight.py
NASA/Mars/__init__.py
NASA/Mars/mars.py
NASA/NEO/__init__.py
NASA/NEO/neo.py
NASA/SSC/__init__.py
NASA/SSC/ssc.py
NASA/SSD_CNEOS/__init__.py
NASA/SSD_CNEOS/ssd_cneos.py
NASA/TLE/__init__.py
NASA/TLE/tle.py
NASA/TechTransfer/__init__.py
NASA/TechTransfer/techtransfer.py
NASA/Techport/__init__.py
NASA/Techport/techport.py
NASA/WMTS/__init__.py
NASA/WMTS/wmts.py
PyAstrum.egg-info/PKG-INFO
PyAstrum.egg-info/SOURCES.txt
PyAstrum.egg-info/dependency_links.txt
PyAstrum.egg-info/requires.txt
PyAstrum.egg-info/top_level.txt
helpers/__init__.py
helpers/config.py
helpers/log.py
tests/__init__.py
tests/ESA/__init__.py
tests/NASA/__init__.py