Metadata-Version: 2.1
Name: PyAstrum
Version: 0.1
Summary: Python SDK for space agencies RESTful APIs
Home-page: https://github.com/ultraeia/PyAstrum
Author: Marcos Jesus Vivar
Author-email: marcos.vivar@protonmail.com
License: MIT License
Download-URL: https://github.com/ultraeia/PyAstrum/archive/0.1.tar.gz
Project-URL: Source, https://github.com/ultraeia/PyAstrum
Platform: UNKNOWN
Classifier: License :: OSI Approved :: MIT License
Classifier: Operating System :: OS Independent
Classifier: Programming Language :: Python :: 3.8
Requires-Python: >=3.8
